setup.py
leancloud/__init__.py
leancloud/_compat.py
leancloud/acl.py
leancloud/app_router.py
leancloud/client.py
leancloud/cloudfunc.py
leancloud/errors.py
leancloud/file_.py
leancloud/geo_point.py
leancloud/mime_type.py
leancloud/object_.py
leancloud/operation.py
leancloud/push.py
leancloud/query.py
leancloud/relation.py
leancloud/role.py
leancloud/user.py
leancloud/utils.py
leancloud/engine/__init__.py
leancloud/engine/authorization.py
leancloud/engine/cloudfunc.py
leancloud/engine/context.py
leancloud/engine/cookie_session.py
leancloud/engine/cors.py
leancloud/engine/https_redirect_middleware.py
leancloud/engine/leanengine.py
leancloud/engine/utils.py
leancloud_sdk_ng.egg-info/PKG-INFO
leancloud_sdk_ng.egg-info/SOURCES.txt
leancloud_sdk_ng.egg-info/dependency_links.txt
leancloud_sdk_ng.egg-info/requires.txt
leancloud_sdk_ng.egg-info/top_level.txt