Metadata-Version: 1.1
Name: leancloud-sdk-ng
Version: 2.0.0
Summary: LeanCloud Python SDK
Home-page: https://leancloud.cn/
Author: ifanrx
Author-email: ifanrx@ifanr.com
License: LGPL
Keywords: Leancloud SDK
Platform: UNKNOWN
Classifier: Development Status :: 4 - Beta
Classifier: Intended Audience :: Developers
Classifier: Programming Language :: Python :: 2
Classifier: Programming Language :: Python :: 2.7
Classifier: Programming Language :: Python :: 3.5
